utilnacki/__init__.py
utilnacki/classes.py
utilnacki/dates.py
utilnacki/lists.py
utilnacki/lists_of_dicts.py
utilnacki/matrix_solver.py
utilnacki/misc.py
utilnacki/panda.py
utilnacki/scraping.py
utilnacki/soup.py
utilnacki/strings.py
utilnacki-0.1.1.dist-info/METADATA
utilnacki-0.1.1.dist-info/WHEEL
utilnacki-0.1.1.dist-info/RECORD
