Metadata-Version: 2.4
Name: utilnacki
Version: 0.1.1
Summary: houses various helpful functions accumulated over time
Requires-Python: >=3.11
Requires-Dist: beautifulsoup4==4.12.3
Requires-Dist: numpy==2.0.1
Requires-Dist: pandas==2.2.2
Requires-Dist: python-dateutil==2.9.0.post0
Requires-Dist: pytz==2024.1
Requires-Dist: requests
Requires-Dist: six==1.16.0
Requires-Dist: tzdata==2024.1
